[
    {
        "post_id": [
            "41"
        ],
        "post_link": "/My-6------th---Post1557059235-721297",
        "post_body": "\nВопрос на автофоруме:\n\nДрузья, случайно монета 5 рублей выпала из кармана и угодила в узкую щель, откуда тянется ремень безопасности. Фонариком светил, кажись провалилась глубоко, не подскажите, есть ли способ достать как-нибудь?\nПервые ответы:\n\nxxx: Придётся продавать машину на 5 рублей дороже.\n\nyyy: Перевернуть машину и потрясти... \n",
        "date_created": "2019-5-5",
        "post_rating": "0"
    },
    {
        "post_id": [
            "5"
        ],
        "post_link": "/5th-post1556477980-34654",
        "post_body": "\nxxx: Полезла подмести под кроватью мужа, нашла коробку с десятком разных носков\n\nxxx: Спросила у него, он сказал: \"это приют для осиротевших носков, иногда они там находят свою пару.\"\n\nxxx: Пару раз в год.\n\nxxx: Питомник, блин.\n",
        "date_created": "2019-4-28",
        "post_rating": "0"
    },
    {
        "post_id": [
            "4"
        ],
        "post_link": "/4th-post1556477706-556497",
        "post_body": "\nXXX: У тебя корел есть на работе?\n\nYYY: Есть.\n\nXXX: Какая версия?\n\nYYY: Х7\n\nXXX: Ясно.Спасибо.\n\nYYY: Какая там последняя?\n\nXXX: ХЗ\n\nXXX: В смысле, не знаю :))))\n",
        "date_created": "2019-4-28",
        "post_rating": "0"
    },
    {
        "post_id": [
            "3"
        ],
        "post_link": "/Third-post1556474921-051282",
        "post_body": "\nxxx: А тут вообще есть кто не любит beanы как я? )))\n\nxxx: spring и тому подобные фреймворки превращают java программиста в xml или annotation программиста.\n\nxxx: Почему-то тихо стало. Я что-то не то сказал?\n\nyyy: Беги\n\nzzz: Вычисляем твое местоположение\n",
        "date_created": "2019-4-28",
        "post_rating": "0"
    },
    {
        "post_id": [
            "1"
        ],
        "post_link": "/First-post",
        "post_body": "\nМаленький мальчик нашел кимано\nПару приемов он видел в кино\nС криком \"кия\"и ударом ноги\nЯ получаю гиги за шаги\n",
        "date_created": "2019-4-14",
        "post_rating": "228"
    },
    {
        "post_id": [
            "2"
        ],
        "post_link": "/Second-post",
        "post_body": "\nИдут металлист и панк. Навстречу — грустный—грустный хиппи.\nПанк: — Что это с тобой???\nХиппи: — В ванной мылся и фенечку потерял...\nМеталлист: — А что такое фенечка?\nПанк: — А что такое ванна?\n",
        "date_created": "2019-4-14",
        "post_rating": "1488"
    }
]